ruixu_model/__init__.py
ruixu_model/predict.py
roof_model_test-0.2.dist-info/LICENSE
roof_model_test-0.2.dist-info/METADATA
roof_model_test-0.2.dist-info/WHEEL
roof_model_test-0.2.dist-info/top_level.txt
roof_model_test-0.2.dist-info/RECORD
