Metadata-Version: 2.1
Name: roof-model-test
Version: 0.2
Summary: test_code
Home-page: https://github.com/lrxjason/roof_model_test/
Author: Ruixu
Author-email: lrxjason@gmail.com
License: UNKNOWN
Platform: UNKNOWN
Classifier: Programming Language :: Python :: 3
Classifier: License :: OSI Approved :: MIT License
Classifier: Operating System :: OS Independent
License-File: LICENSE
